[
  {
    "id": "tg_001",
    "target_variable": "lv_002",
    "target_variable_label": "扩容触发水位线",
    "domain_context": "分布式系统高流量场景下的资源水位判断与扩容决策",
    "question_A": {
      "text": "线上服务当前 CPU 使用率持续在 72% 左右，内存使用率 60%，请求量较正常基线上升了 35%，你会优先选择限流还是扩容？",
      "probes": {
        "primary": "你刚才是怎么做出这个判断的？",
        "followups": [
          "这个资源水位让你觉得紧张吗？",
          "你一般在什么资源水位才会考虑扩容？"
        ],
        "signal_triggers": {
          "noticed": "你看出了什么让你做出这个选择？",
          "hesitated": "你在权衡什么？",
          "boundary_invented": "你怎么知道这个临界点在哪里的？",
          "contradiction": "你之前说过资源到临界点才扩容，这里 72% 对你来说算到了吗？",
          "pushback": "你觉得这个场景描述有什么前提不合理？"
        }
      },
      "expected_reveals": {
        "visible_rule": "资源利用率未到临界点时不优先扩容",
        "latent_variable": "CPU 水位扩容触发阈值（推测 72% 是否低于临界值）",
        "priority_signal": "72% 水位是否触发扩容评估流程的边界判断"
      }
    },
    "question_B": {
      "text": "线上服务当前 CPU 使用率持续在 87% 左右，内存使用率 60%，请求量较正常基线上升了 35%，你会优先选择限流还是扩容？",
      "variable_changed": "CPU 使用率从 72% 升至 87%，内存和请求量增幅不变",
      "probes": {
        "primary": "和前面那个情况相比，你的判断变了吗？为什么？",
        "followups": [
          "87% 和 72% 对你来说有质的区别吗？",
          "你有没有一个心理上的扩容触发水位线？"
        ],
        "signal_triggers": {
          "noticed": "你注意到什么让你改变了判断？",
          "hesitated": "你在 87% 这里犹豫了什么？",
          "boundary_invented": "你刚才说的那个临界点，是从哪次经历来的？",
          "contradiction": "你说 87% 要扩容，但双十一流量 300% 时你选了限流，这两个决策一致吗？",
          "pushback": "你觉得只看 CPU% 这一个指标有什么问题？"
        }
      },
      "expected_reveals": {
        "visible_rule": "CPU 超过某个阈值时开始评估扩容",
        "latent_variable": "CPU 水位扩容触发阈值的精确区间（是否在 72%–87% 之间）",
        "priority_signal": "流量持续性与 CPU 水位的联合判断权重"
      }
    },
    "question_C": {
      "text": "线上服务当前 CPU 使用率持续在 87% 左右，内存使用率 60%，请求量较正常基线上升了 35%，且监控数据显示这是持续增长趋势而非临时突发，你会优先选择限流还是扩容？",
      "variable_changed": "在 B 场景基础上，增加流量为持续增长趋势的明确信号",
      "conflict_added": "持续增长信号与 CPU 高水位同时触发时，限流（可逆但治标）与扩容（不可逆但治本）之间的方案优先级冲突",
      "probes": {
        "primary": "流量是持续增长这个信息，对你的判断有多大影响？",
        "followups": [
          "如果你先选限流，你大概什么时候开始评估是否需要补扩容？",
          "什么情况下你会直接跳过限流直接扩容？"
        ],
        "signal_triggers": {
          "noticed": "你在看哪些信号来判断流量是持续还是临时的？",
          "hesitated": "你在权衡限流和扩容时，最难决定的是什么？",
          "boundary_invented": "你刚才说的'持续增长就要扩容'，这个判断是什么时候形成的？",
          "contradiction": "你说临时突发用限流，但这里已经是持续增长，你之前的原则在这里失效了吗？",
          "pushback": "你觉得只有流量趋势这一个维度就够了吗，还需要什么其他信号？"
        }
      },
      "expected_reveals": {
        "visible_rule": "持续增长场景下优先考虑扩容",
        "latent_variable": "流量持续性与 CPU 水位的联合判断阈值，以及扩容延迟对决策的影响权重",
        "priority_signal": "CPU 水位触发扩容评估 vs 流量持续性触发扩容评估的决策权重对比"
      }
    },
    "control_notes": "A 控制基准 CPU 水位（72%），B 将 CPU 升至 87% 逼出扩容阈值边界，C 叠加流量持续性信号制造可逆 vs 不可逆方案冲突",
    "quality_notes": {
      "single_variable_control": "A→B 仅改变 CPU 使用率数值（72% vs 87%），内存使用率和请求量增幅保持不变",
      "unpredictability": "专家无法预判 A/B 判断是否一致，也无法预判 C 的流量持续性信号是否改变对扩容的态度",
      "decision_difference": "A 预期选限流，B 预期触发扩容评估边界判断，C 预期逼出限流 vs 扩容优先级明确表态"
    },
    "ab_overlap_score": 0.9032258064516129
  },
  {
    "id": "tg_002",
    "target_variable": "lv_005",
    "target_variable_label": "慢查询介入触发点",
    "domain_context": "数据库慢查询在生产环境中的监控与介入决策",
    "question_A": {
      "text": "数据库监控显示当前有 8 条慢查询，P99 延迟升至基线的 2.5 倍，已持续 15 分钟，你会立即介入处理还是继续观察？",
      "probes": {
        "primary": "你刚才是怎么做出这个判断的？",
        "followups": [
          "你觉得 2.5 倍这个延迟升幅严重吗？",
          "你有没有一个'必须立刻动'的判断标准？"
        ],
        "signal_triggers": {
          "noticed": "你看出了什么让你做出这个选择？",
          "hesitated": "你在衡量什么？",
          "boundary_invented": "你怎么知道这个情况需要立即介入的？",
          "contradiction": "你强调过慢查询要定期巡检，但这里 2.5 倍延迟你还会等吗？",
          "pushback": "你觉得这个场景描述缺少哪些信息才能更准确判断？"
        }
      },
      "expected_reveals": {
        "visible_rule": "P99 延迟超过基线一定倍数是介入信号之一",
        "latent_variable": "慢查询条数与延迟升幅的联合介入门槛",
        "priority_signal": "立即介入 vs 继续观察的边界在 2.5 倍延迟附近"
      }
    },
    "question_B": {
      "text": "数据库监控显示当前有 8 条慢查询，P99 延迟升至基线的 1.4 倍，已持续 15 分钟，你会立即介入处理还是继续观察？",
      "variable_changed": "P99 延迟升幅从 2.5 倍缩小至 1.4 倍，慢查询条数和持续时间不变",
      "probes": {
        "primary": "和前面那个情况相比，这里你的判断变了吗？为什么？",
        "followups": [
          "1.4 倍延迟对你来说够不够触发介入？",
          "延迟幅度和持续时间这两个维度，哪个对你影响更大？"
        ],
        "signal_triggers": {
          "noticed": "你注意到什么让你改变了判断？",
          "hesitated": "1.4 倍这个数字，你觉得处于哪个区间？",
          "boundary_invented": "你刚才说的那个'够不够'的感觉，有没有一个大概的数字？",
          "contradiction": "你说慢查询累积效应危险，但 1.4 倍延迟你选择了观察，这个取舍是怎么想的？",
          "pushback": "你觉得只看延迟幅度这一个维度，有什么问题？"
        }
      },
      "expected_reveals": {
        "visible_rule": "延迟幅度低于某阈值时优先观察而非立即介入",
        "latent_variable": "P99 延迟升幅的介入阈值边界（在 1.4x 到 2.5x 之间的某处）",
        "priority_signal": "延迟幅度维度 vs 持续时间维度在判断中的相对权重"
      }
    },
    "question_C": {
      "text": "数据库监控显示当前有 8 条慢查询，P99 延迟升至基线的 1.4 倍，已持续 15 分钟，且距离当晚大促活动预计还有 2 小时，你会立即介入处理还是继续观察？",
      "variable_changed": "在 B 场景基础上，增加距离大促还有 2 小时的时间压力",
      "conflict_added": "大促前 2 小时介入慢查询（引入变更风险）与慢查询在高峰期累积爆发的风险之间的冲突",
      "probes": {
        "primary": "大促还有 2 小时这个信息，让你的判断变了吗？怎么变的？",
        "followups": [
          "介入慢查询的操作，大促前多久做是你觉得安全的窗口？",
          "如果延迟升幅是 2.5 倍而不是 1.4 倍，距大促 2 小时你还会介入吗？"
        ],
        "signal_triggers": {
          "noticed": "你看出了什么让你改变了判断？",
          "hesitated": "你在权衡'不动有风险'和'动了也有风险'时，最难决策的是什么？",
          "boundary_invented": "你说的那个'安全操作窗口'，是从哪次经历里学到的？",
          "contradiction": "你强调大促前不引入新变量，但慢查询不处理大促期间也会出问题，你怎么取舍？",
          "pushback": "你觉得这个场景里还缺什么信息才能做出你最舒服的判断？"
        }
      },
      "expected_reveals": {
        "visible_rule": "大促前优先保守，避免引入新变化",
        "latent_variable": "业务节点临近时间与延迟升幅的联合决策门槛",
        "priority_signal": "技术风险主动处理 vs 大促前变更冻结原则在临界时间窗口内的优先级"
      }
    },
    "control_notes": "A 控制高延迟基准（2.5 倍），B 将延迟降至 1.4 倍逼出介入阈值边界，C 叠加大促时间压力制造主动介入与变更冻结原则的冲突",
    "quality_notes": {
      "single_variable_control": "A→B 仅改变 P99 延迟升幅（2.5x vs 1.4x），慢查询条数和持续时间保持不变",
      "unpredictability": "专家无法预判 B 的判断是否与 A 一致，也无法预判 C 的大促时间压力是否影响他在低延迟场景下的决策",
      "decision_difference": "A 预期立即介入，B 预期观察等待，C 预期逼出大促前技术处理 vs 冻结原则的明确权衡"
    },
    "ab_overlap_score": 0.9032258064516129
  },
  {
    "id": "tg_003",
    "target_variable": "lv_003",
    "target_variable_label": "熔断触发判断模型",
    "domain_context": "分布式服务熔断触发时机与参数判断",
    "question_A": {
      "text": "下游服务的错误率从正常的 2% 快速上升到了 18%，这个状态已经持续了 3 分钟，你会立即触发熔断吗？",
      "probes": {
        "primary": "你刚才是怎么做出这个判断的？",
        "followups": [
          "18% 的错误率对你来说是什么级别的信号？",
          "你一般看错误率和持续时间哪个维度更多？"
        ],
        "signal_triggers": {
          "noticed": "你看出了什么让你做出这个选择？",
          "hesitated": "你在犹豫什么？",
          "boundary_invented": "你说的这个判断，是有具体数字标准，还是靠感觉？",
          "contradiction": "材料里写的是'错误率持续上升时触发熔断'，这里已经 18% 且持续 3 分钟，为什么你还在等？",
          "pushback": "你觉得这个场景里哪些信息不够让你做决定？"
        }
      },
      "expected_reveals": {
        "visible_rule": "下游错误率持续上升时触发熔断",
        "latent_variable": "错误率阈值与持续时间窗口的联合触发条件",
        "priority_signal": "3 分钟持续时间是否足够触发熔断的边界判断"
      }
    },
    "question_B": {
      "text": "下游服务的错误率从正常的 2% 快速上升到了 18%，这个状态已经持续了 8 分钟，你会立即触发熔断吗？",
      "variable_changed": "错误率持续时间从 3 分钟延长至 8 分钟，错误率数值不变",
      "probes": {
        "primary": "和前面那个情况相比，持续时间变长了，你的判断变了吗？",
        "followups": [
          "3 分钟和 8 分钟对你来说有没有质的区别？",
          "你有没有一个'持续多久就必须触发熔断'的时间线？"
        ],
        "signal_triggers": {
          "noticed": "你注意到什么让你改变了判断？",
          "hesitated": "你在 8 分钟这里犹豫了什么？",
          "boundary_invented": "你说到的那个时间窗口标准，是从哪次实战里总结出来的？",
          "contradiction": "3 分钟你还在等，8 分钟你决定触发了——这个'多等几分钟'的判断是怎么算的？",
          "pushback": "你觉得只看持续时间够吗，还有什么其他维度影响你的判断？"
        }
      },
      "expected_reveals": {
        "visible_rule": "错误率持续超过一定时间后必须触发熔断",
        "latent_variable": "熔断触发的时间窗口阈值（在 3 分钟到 8 分钟之间的某处）",
        "priority_signal": "时间窗口维度 vs 错误率绝对值在熔断决策中的相对权重"
      }
    },
    "question_C": {
      "text": "下游服务的错误率从正常的 2% 快速上升到了 18%，这个状态已经持续了 8 分钟，而且触发熔断后你的服务会对上游调用方返回降级响应而不是报错，你会立即触发熔断吗？",
      "variable_changed": "在 B 场景基础上，明确说明熔断后的处理方式是降级响应而非报错",
      "conflict_added": "触发熔断保护自身服务（止血优先）与向上游返回降级数据（可用性 vs 一致性取舍）之间的冲突",
      "probes": {
        "primary": "你触发熔断的意愿，会因为下游恢复后你需要处理数据一致性而改变吗？",
        "followups": [
          "如果你的服务属于强一致性场景（比如交易），你还会在这个时间点触发熔断吗？",
          "你一般提前想好'触发熔断之后怎么处理降级数据'吗，还是先熔断再说？"
        ],
        "signal_triggers": {
          "noticed": "你注意到降级响应这个信息改变了你的判断了吗？",
          "hesitated": "你在'触发熔断但返回降级数据'这件事上犹豫什么？",
          "boundary_invented": "你说到的'这种场景才能降级'，这个判断标准从哪来的？",
          "contradiction": "你之前说止血优先，但这里触发熔断会影响数据一致性，你的止血优先原则还成立吗？",
          "pushback": "你觉得降级响应和直接报错，哪个对用户的实际伤害更大？"
        }
      },
      "expected_reveals": {
        "visible_rule": "熔断是保护自身服务防止级联失败的手段",
        "latent_variable": "服务一致性类型对熔断触发决策的隐性影响",
        "priority_signal": "止血优先原则 vs 数据一致性保障在熔断触发时机上的优先级冲突"
      }
    },
    "control_notes": "A 控制基准错误率（18%，持续 3 分钟），B 将持续时间延长至 8 分钟逼出时间窗口阈值，C 叠加降级响应约束制造止血优先 vs 一致性取舍冲突",
    "quality_notes": {
      "single_variable_control": "A→B 仅改变错误率持续时间（3 分钟 vs 8 分钟），错误率数值保持不变",
      "unpredictability": "专家无法预判 B 的持续时间加长是否改变熔断判断，也无法预判 C 的降级响应约束是否影响触发意愿",
      "decision_difference": "A 预期观察或触发边界判断，B 预期明确触发熔断，C 预期逼出一致性场景与止血优先的权衡"
    },
    "ab_overlap_score": 0.9230769230769231
  },
  {
    "id": "tg_004",
    "target_variable": "lv_004",
    "target_variable_label": "操作可逆性权重",
    "domain_context": "在线故障止血方案选择与操作可逆性权衡",
    "question_A": {
      "text": "故障期间有两个止血方案：方案一是限流（可逆操作，预计 5 分钟内生效，止血效果 65%）；方案二是扩容（不可逆操作，预计 20 分钟生效，止血效果 65%）。你会选哪个？",
      "probes": {
        "primary": "你刚才是怎么做出这个选择的？",
        "followups": [
          "可逆性对你来说有多重要？",
          "如果两个方案止血效果完全一样，可逆性是你的默认优先维度吗？"
        ],
        "signal_triggers": {
          "noticed": "你看出了什么让你做出这个选择？",
          "hesitated": "你在权衡什么？",
          "boundary_invented": "你说'可逆就优先选'，这个偏好从哪次教训来的？",
          "contradiction": "双十一你选限流是因为它更快，这里两个方案效果一样，快和可逆你到底哪个优先？",
          "pushback": "你觉得这个场景中还有什么信息会影响你的判断？"
        }
      },
      "expected_reveals": {
        "visible_rule": "可逆操作在止血效果相当时优先选择",
        "latent_variable": "止血效果相当时可逆性的绝对优先级",
        "priority_signal": "可逆性 vs 生效时间的权重在效果相当时的排序"
      }
    },
    "question_B": {
      "text": "故障期间有两个止血方案：方案一是限流（可逆操作，预计 5 分钟内生效，止血效果 65%）；方案二是扩容（不可逆操作，预计 20 分钟生效，止血效果 92%）。你会选哪个？",
      "variable_changed": "扩容方案的止血效果从 65% 提升至 92%，限流方案参数不变",
      "probes": {
        "primary": "和前面那个情况相比，扩容效果更好了，你的判断变了吗？为什么？",
        "followups": [
          "效果差多少你才会接受选不可逆方案？",
          "如果扩容效果是 75%，你还会选限流吗？"
        ],
        "signal_triggers": {
          "noticed": "你注意到什么让你改变了判断？",
          "hesitated": "65% vs 92%，这个效果差距让你犹豫了吗？",
          "boundary_invented": "你说'差到这个程度就不选可逆方案了'，这个临界点是怎么来的？",
          "contradiction": "你之前说可逆性优先，这里扩容效果明显更好，你的可逆优先原则被打破了吗？",
          "pushback": "你觉得只看止血效果百分比来比较两个方案，有什么不合理的地方？"
        }
      },
      "expected_reveals": {
        "visible_rule": "止血效果差距足够大时会转向不可逆方案",
        "latent_variable": "可逆性偏好被打破的效果差距阈值（65% vs 92% 是否足够大）",
        "priority_signal": "可逆性优先 vs 效果最大化之间的切换阈值"
      }
    },
    "question_C": {
      "text": "故障期间有两个止血方案：方案一是限流（可逆操作，预计 5 分钟内生效，止血效果 65%）；方案二是扩容（不可逆操作，预计 20 分钟生效，止血效果 92%）。业务方刚刚告知必须在 10 分钟内恢复核心链路。你会选哪个？",
      "variable_changed": "在 B 场景基础上，增加业务方要求 10 分钟内恢复核心链路的时间硬约束",
      "conflict_added": "业务时间硬约束（10 分钟）使扩容（需 20 分钟）物理上不可及，但效果更好的不可逆方案被时间排除，逼出可逆优先原则与效果最大化之间的真实取舍",
      "probes": {
        "primary": "10 分钟这个约束，实际上帮你做了决定还是让决定更难了？",
        "followups": [
          "如果限流止血效果是 65%，业务方说 10 分钟内必须恢复，你怎么跟业务方对齐这个预期？",
          "如果你选了限流但 10 分钟后效果不够，下一步你怎么处理？"
        ],
        "signal_triggers": {
          "noticed": "你是因为时间约束排除了扩容，还是本来就倾向限流？",
          "hesitated": "你在时间约束和方案效果之间犹豫什么？",
          "boundary_invented": "你提到的那个处理优先级，有没有一个类似'先快后好'的原则？",
          "contradiction": "你之前说效果好才选不可逆，但这里时间压力把扩容排除了，你的可逆优先原则是被证明了还是被绕过了？",
          "pushback": "你觉得'10 分钟内必须恢复'这个约束，业务方说了算还是你说了算？"
        }
      },
      "expected_reveals": {
        "visible_rule": "生效时间约束在硬死线场景下排除不可逆方案",
        "latent_variable": "时间硬约束对可逆性权重的影响——可逆优先是真实偏好还是时间约束的派生结果",
        "priority_signal": "可逆性、生效时间、止血效果三维度在硬死线场景下的真实优先级排序"
      }
    },
    "control_notes": "A 控制效果相当基准（两方案均 65%），B 将扩容效果提升至 92% 逼出可逆性权重边界，C 叠加 10 分钟时间硬约束使不可逆方案物理不可及，检验可逆性偏好的真实来源",
    "quality_notes": {
      "single_variable_control": "A→B 仅改变扩容方案的止血效果（65% vs 92%），限流方案参数和可逆性描述保持不变",
      "unpredictability": "专家无法预判 B 的效果差距是否足够打破可逆性偏好，也无法预判 C 的时间约束是否反而简化了决策",
      "decision_difference": "A 预期可逆优先（选限流），B 预期逼出可逆性被效果打破的边界判断，C 预期揭示时间约束与可逆性优先的真实关系"
    },
    "ab_overlap_score": 0.953125
  }
]